{
  "parent": "minecraft:recipes/root",
  "criteria": {
    "has_rose_pink_salt_bricks": {
      "conditions": {
        "items": [
          {
            "items": [
              "galosphere:rose_pink_salt_bricks"
            ]
          }
        ]
      },
      "trigger": "minecraft:inventory_changed"
    },
    "has_the_recipe": {
      "conditions": {
        "recipe": "galosphere:rose_pink_salt_brick_stairs"
      },
      "trigger": "minecraft:recipe_unlocked"
    }
  },
  "requirements": [
    [
      "has_rose_pink_salt_bricks",
      "has_the_recipe"
    ]
  ],
  "rewards": {
    "recipes": [
      "galosphere:rose_pink_salt_brick_stairs"
    ]
  },
  "sends_telemetry_event": false
}