{
  "parent": "minecraft:recipes/root",
  "rewards": {
    "recipes": [
      "galosphere:mysteria_cinders"
    ]
  },
  "criteria": {
    "has_mysteria_vines": {
      "trigger": "minecraft:inventory_changed",
      "conditions": {
        "items": [
          {
            "items": [
              "galosphere:mysteria_vines"
            ]
          }
        ]
      }
    },
    "has_the_recipe": {
      "trigger": "minecraft:recipe_unlocked",
      "conditions": {
        "recipe": "galosphere:mysteria_cinders"
      }
    }
  },
  "requirements": [
    [
      "has_mysteria_vines",
      "has_the_recipe"
    ]
  ]
}