{
  "parent": "minecraft:recipes/root",
  "rewards": {
    "recipes": [
      "minecraft:amethyst_bricks_from_smooth_amethyst_stonecutting"
    ]
  },
  "criteria": {
    "has_smooth_amethyst": {
      "trigger": "minecraft:inventory_changed",
      "conditions": {
        "items": [
          {
            "items": [
              "cavesandtrenches:smooth_amethyst"
            ]
          }
        ]
      }
    },
    "has_the_recipe": {
      "trigger": "minecraft:recipe_unlocked",
      "conditions": {
        "recipe": "minecraft:amethyst_bricks_from_smooth_amethyst_stonecutting"
      }
    }
  },
  "requirements": [
    [
      "has_smooth_amethyst",
      "has_the_recipe"
    ]
  ]
}